gatilegrid/__init__.py
gatilegrid/grid.py
gatilegrid/tilegrids.py
gatilegrid-1.0.1.dist-info/licenses/LICENSE
gatilegrid-1.0.1.dist-info/METADATA
gatilegrid-1.0.1.dist-info/WHEEL
gatilegrid-1.0.1.dist-info/top_level.txt
gatilegrid-1.0.1.dist-info/RECORD
