Metadata-Version: 2.4
Name: gatilegrid
Version: 1.0.1
Summary: Popular tile grids and grids API for web mapping applications
Author-email: Loic Gasser <loicgasser4@gmail.com>
License-Expression: MIT
Project-URL: Homepage, https://github.com/geoadmin/lib-gatilegrid
Project-URL: Documentation, https://github.com/geoadmin/lib-gatilegrid#readme
Project-URL: Source, https://github.com/geoadmin/lib-gatilegrid
Project-URL: Tracker, https://github.com/geoadmin/lib-gatilegrid/issues
Keywords: gis,wmts,grid,map
Classifier: Development Status :: 5 - Production/Stable
Classifier: Intended Audience :: Developers
Classifier: Operating System :: OS Independent
Classifier: Programming Language :: Python
Classifier: Programming Language :: Python :: 3
Classifier: Topic :: Scientific/Engineering :: GIS
Classifier: Topic :: Software Development :: Libraries :: Python Modules
Requires-Python: >=3.0
License-File: LICENSE
Dynamic: license-file
